sqlite_zstd/libsqlite_zstd.abi3.so
sqlite_zstd/datasette.py
sqlite_zstd/__init__.py
sqlite_zstd_build-0.3.2.41.dist-info/entry_points.txt
sqlite_zstd_build-0.3.2.41.dist-info/WHEEL
sqlite_zstd_build-0.3.2.41.dist-info/top_level.txt
sqlite_zstd_build-0.3.2.41.dist-info/RECORD
sqlite_zstd_build-0.3.2.41.dist-info/METADATA
