Metadata-Version: 2.1
Name: sqlite-zstd-build
Version: 0.3.2.41
Requires-Python: >=3.9
